co2mpas_driver/README.md
co2mpas_driver/__init__.py
co2mpas_driver/_version.py
co2mpas_driver/euro_segment.py
co2mpas_driver/load.py
co2mpas_driver/plot.py
co2mpas_driver/sample_simulation.py
co2mpas_driver/common/__init__.py
co2mpas_driver/common/defaults.py
co2mpas_driver/common/functions.py
co2mpas_driver/common/gear_functions.py
co2mpas_driver/common/generic_co2mpas.py
co2mpas_driver/common/plot_templates.py
co2mpas_driver/common/reading_n_organizing.py
co2mpas_driver/common/simulation_part.py
co2mpas_driver/common/utils.py
co2mpas_driver/common/vehicle_functions.py
co2mpas_driver/common/vehicle_specs_class.py
co2mpas_driver/db/EuroSegmentCar.csv
co2mpas_driver/db/EuroSegmentCar_cleaned.csv
co2mpas_driver/db/EuroSegmentCar_cleaned_yl.csv
co2mpas_driver/examples/Sim_Kat_for_Jaime_2.py
co2mpas_driver/examples/__init__.py
co2mpas_driver/examples/calculate_on_existing_example.py
co2mpas_driver/examples/mfc_post_proc_trajectory.py
co2mpas_driver/examples/new_test.py
co2mpas_driver/examples/sample_acc_dec_bounds_per_gear.py
co2mpas_driver/examples/sample_gear_shifting.py
co2mpas_driver/examples/sample_light_co2mpas.py
co2mpas_driver/examples/sample_simulation.py
co2mpas_driver/examples/sample_varying_des_speed.py
co2mpas_driver/examples/sample_varying_des_speed_yl_2.py
co2mpas_driver/examples/sample_veh_specs_collection.py
co2mpas_driver/examples/test.py
co2mpas_driver/model/__init__.py
co2mpas_driver/model/co2mpas.py
co2mpas_driver/model/driver.py
co2mpas_driver/model/simulation.py
co2mpas_driver/template/sample.xlsx
model_validation/__init__.py
model_validation/test_core.py
model_validation/test_model.py
model_validation/utils.py
co2mpas_driver-1.3.3.dist-info/AUTHORS.rst
co2mpas_driver-1.3.3.dist-info/LICENSE.txt
co2mpas_driver-1.3.3.dist-info/METADATA
co2mpas_driver-1.3.3.dist-info/WHEEL
co2mpas_driver-1.3.3.dist-info/entry_points.txt
co2mpas_driver-1.3.3.dist-info/top_level.txt
co2mpas_driver-1.3.3.dist-info/zip-safe
co2mpas_driver-1.3.3.dist-info/RECORD
