Metadata-Version: 2.1
Name: co2mpas-driver
Version: 1.3.3
Summary: A lightweight microsimulation free-flow acceleration model(MFC) or co2mpas_driver is a model that is able to capture the vehicle acceleration dynamics accurately and consistently
License: European Union Public Licence 1.1 or later (EUPL 1.1+)
Project-URL: Sources, https://code.europa.eu/jrc-ldv/co2mpas_driver
Platform: any
Classifier: Development Status :: 4 - Beta
Classifier: Intended Audience :: Developers
Classifier: Intended Audience :: Science/Research
Classifier: Intended Audience :: Manufacturing
Classifier: Programming Language :: Python :: 3
Classifier: Programming Language :: Python :: 3.5
Classifier: Programming Language :: Python :: 3.6
Classifier: Programming Language :: Python :: 3.7
Classifier: Programming Language :: Python :: Implementation :: CPython
Classifier: Natural Language :: English
Classifier: Environment :: Console
Classifier: Operating System :: MacOS :: MacOS X
Classifier: Operating System :: Microsoft :: Windows
Classifier: Operating System :: POSIX
Classifier: Operating System :: Unix
License-File: LICENSE.txt
License-File: AUTHORS.rst
Requires-Dist: PyYAML
Requires-Dist: schedula[all] (>=0.3.2)
Requires-Dist: tqdm
Requires-Dist: scikit-learn
Requires-Dist: regex
Requires-Dist: lmfit (>=0.9.7)
Requires-Dist: numpy
Requires-Dist: schema
Requires-Dist: scipy
Requires-Dist: wltp
Requires-Dist: xgboost
Requires-Dist: pandas
Requires-Dist: networkx
